hackeeg/__init__.py
hackeeg/__version__.py
hackeeg/ads1299.py
hackeeg/driver.py
hackeeg-0.3.0.data/scripts/example.py
hackeeg-0.3.0.data/scripts/hackeeg_shell
hackeeg-0.3.0.data/scripts/hackeeg_shell.py
hackeeg-0.3.0.data/scripts/hackeeg_stream
hackeeg-0.3.0.data/scripts/hackeeg_stream.py
hackeeg-0.3.0.data/scripts/lsl_receive_data.py
hackeeg-0.3.0.data/scripts/simple_lsl_receive_and_plot.py
hackeeg-0.3.0.dist-info/LICENSE
hackeeg-0.3.0.dist-info/METADATA
hackeeg-0.3.0.dist-info/WHEEL
hackeeg-0.3.0.dist-info/top_level.txt
hackeeg-0.3.0.dist-info/RECORD
