Metadata-Version: 2.1
Name: hackeeg
Version: 0.3.0
Summary: Python client library for HackEEG Arduino Due shield
Home-page: http://github.com/starcat-io/hackeeg-client-python
Author: Starcat LLC
Author-email: adam@starcat.io
License: Apache 2.0
Platform: UNKNOWN
Requires-Dist: pyserial
Requires-Dist: bitstring
Requires-Dist: numpy
Requires-Dist: jsonlines
Requires-Dist: msgpack
Requires-Dist: autopep8
Requires-Dist: gnureadline
Requires-Dist: pylsl
